kuqezeze
