Metadata-Version: 2.1
Name: kuqezeze
Version: 2.0.0
Summary: A package that guess the munber
Home-page: UNKNOWN
Author: Guido Xhindoli
Author-email: <mail@gmail.com>
License: UNKNOWN
Keywords: kuqezeze,kuqe,zeze,sda
Platform: UNKNOWN
Classifier: Development Status :: 1 - Planning
Classifier: Intended Audience :: Developers
Classifier: Programming Language :: Python :: 3
Classifier: Operating System :: Unix
Classifier: Operating System :: MacOS :: MacOS X
Classifier: Operating System :: Microsoft :: Windows
